forsyde/__init__.py
forsyde/io/__init__.py
forsyde/io/python/__init__.py
forsyde/io/python/api.py
forsyde/io/python/core.py
forsyde/io/python/drivers.py
forsyde/io/python/ports.py
forsyde/io/python/types.py
forsyde/py.typed
forsyde_io_python-0.3.6.dist-info/LICENSE
forsyde_io_python-0.3.6.dist-info/WHEEL
forsyde_io_python-0.3.6.dist-info/METADATA
forsyde_io_python-0.3.6.dist-info/RECORD
