Metadata-Version: 2.1
Name: forsyde-io-python
Version: 0.3.6
Summary: Python supporting libraries for ForSyDe IO
Home-page: https://forsyde.github.io/forsyde-io/
License: MIT
Author: Rodolfo
Author-email: jordao@kth.se
Requires-Python: >=3.7,<4.0
Classifier: License :: OSI Approved :: MIT License
Classifier: Programming Language :: Python :: 3
Classifier: Programming Language :: Python :: 3.7
Classifier: Programming Language :: Python :: 3.8
Classifier: Programming Language :: Python :: 3.9
Requires-Dist: networkx (>=2.5,<3.0)
Requires-Dist: pydot (>=1.4.2,<2.0.0)
Project-URL: Documentation, https://forsyde.github.io/forsyde-io/
Project-URL: Repository, https://github.com/forsyde/forsyde-io
